[
  {
    "id_classroom": 1,
    "name": "Lập trình Python",
    "begin_date": "2024-09-02",
    "end_date": "2025-12-31",
    "day_of_week_begin": 2,
    "begin_time": "07:30:00.000000",
    "end_time": "10:30:00.000000",
    "id_lecturer_id": "1079440959"
  },
  {
    "id_classroom": 2,
    "name": "Cấu trúc dữ liệu và giải thuật",
    "begin_date": "2024-09-02",
    "end_date": "2025-12-31",
    "day_of_week_begin": 3,
    "begin_time": "13:00:00.000000",
    "end_time": "16:00:00.000000",
    "id_lecturer_id": "1250767097"
  },
  {
    "id_classroom": 3,
    "name": "Cơ sở dữ liệu",
    "begin_date": "2024-09-02",
    "end_date": "2025-12-31",
    "day_of_week_begin": 4,
    "begin_time": "07:30:00.000000",
    "end_time": "10:30:00.000000",
    "id_lecturer_id": "1304868666"
  },
  {
    "id_classroom": 4,
    "name": "Lập trình Web",
    "begin_date": "2024-09-02",
    "end_date": "2025-12-31",
    "day_of_week_begin": 5,
    "begin_time": "13:00:00.000000",
    "end_time": "16:00:00.000000",
    "id_lecturer_id": "1079440959"
  },
  {
    "id_classroom": 5,
    "name": "Trí tuệ nhân tạo",
    "begin_date": "2024-09-02",
    "end_date": "2025-12-31",
    "day_of_week_begin": 6,
    "begin_time": "07:30:00.000000",
    "end_time": "10:30:00.000000",
    "id_lecturer_id": "1250767097"
  },
  {
    "id_classroom": 6,
    "name": "Mạng máy tính",
    "begin_date": "2024-09-02",
    "end_date": "2024-12-20",
    "day_of_week_begin": 2,
    "begin_time": "07:30:00.000000",
    "end_time": "10:30:00.000000",
    "id_lecturer_id": "1304868666"
  },
  {
    "id_classroom": 7,
    "name": "Hệ điều hành",
    "begin_date": "2024-09-03",
    "end_date": "2024-12-20",
    "day_of_week_begin": 3,
    "begin_time": "13:00:00.000000",
    "end_time": "16:00:00.000000",
    "id_lecturer_id": "1250767097"
  },
  {
    "id_classroom": 8,
    "name": "Lập trình Java",
    "begin_date": "2024-09-04",
    "end_date": "2024-12-20",
    "day_of_week_begin": 4,
    "begin_time": "07:30:00.000000",
    "end_time": "10:30:00.000000",
    "id_lecturer_id": "1079440959"
  }
]